README.rst
setup.py
pyviewx.pygame.egg-info/PKG-INFO
pyviewx.pygame.egg-info/SOURCES.txt
pyviewx.pygame.egg-info/dependency_links.txt
pyviewx.pygame.egg-info/namespace_packages.txt
pyviewx.pygame.egg-info/requires.txt
pyviewx.pygame.egg-info/top_level.txt
pyviewx/pygame/__init__.py
pyviewx/pygame/calibrator.py
pyviewx/pygame/calibratorGL.py