Metadata-Version: 1.0
Name: pyviewx.pygame
Version: 0.5.0
Summary: A pygame calibration scene for use with PyViewX
Home-page: https://github.com/RyanHope/PyViewX
Author: Ryan Hope
Author-email: rmh3093@gmail.com
License: GPL-3
Platform: UNKNOWN
Classifier: License :: OSI Approved :: GNU General Public License (GPL)
Classifier: Framework :: Twisted
Classifier: Programming Language :: Python :: 2
Classifier: Topic :: Scientific/Engineering
Classifier: Topic :: Utilities
Classifier: Topic :: Software Development :: Libraries :: pygame
